{
  "title": "Behind the Edit: Our Process from Raw Footage to Final Cut",
  "slug": "behind-the-edit",
  "excerpt": "Every great video goes through a meticulous editing process. We break down our workflow — from ingesting footage and organizing timelines to sound design and final delivery.",
  "content": "Ever wondered what happens between receiving raw footage and delivering a polished final video? At KV Media Works, our editing process is systematic, creative, and designed to deliver consistent quality across every project.\n\n## Phase 1: Ingestion & Organization\n\nThe first step is always organizing the raw materials. We create a structured folder system, label clips, sync audio, and create proxy files for smoother editing.\n\n**Key steps:**\n- Import and back up all footage\n- Create folder structure (A-roll, B-roll, Audio, Graphics)\n- Sync multi-camera footage\n- Generate proxy files for 4K+ footage\n\n## Phase 2: Assembly Cut\n\nThe assembly cut is the skeleton of the video. We lay out all usable footage in chronological order, creating a rough timeline that captures the overall narrative.\n\n## Phase 3: Rough Cut\n\nThis is where the story starts taking shape. We trim clips, arrange sequences, and begin building the pacing that will drive the final video.\n\n**Focus areas:**\n- Story structure and flow\n- Pacing and rhythm\n- Key messaging alignment\n- B-roll placement\n\n## Phase 4: Fine Cut\n\nThe fine cut is about precision. Every frame matters. We refine transitions, adjust timing down to individual frames, and ensure the video flows seamlessly.\n\n## Phase 5: Sound Design & Music\n\nAudio is 50% of the viewing experience. We add music, sound effects, and ensure dialogue is crystal clear with proper levels and mixing.\n\n## Phase 6: Color Grading\n\nThe visual mood is set through professional color grading, creating consistency and cinematic appeal across the entire video.\n\n## Phase 7: Graphics & Motion\n\nTitles, lower thirds, logos, and any motion graphics are added and animated to enhance the visual narrative.\n\n## Phase 8: Review & Delivery\n\nThe final video goes through internal quality checks before being shared with the client. We provide revision rounds and deliver in all required formats.\n\nThis systematic approach ensures that every video we produce at KV Media Works meets our high standards of quality and creativity.",
  "coverImage": "",
  "author": "KV Media Works",
  "category": "Behind the Scenes",
  "publishedAt": "2025-02-09T18:30:00.000Z",
  "updatedAt": "2025-02-09T18:30:00.000Z",
  "status": "published",
  "tags": [
    "Behind the Scenes"
  ],
  "metaTitle": "",
  "metaDescription": ""
}